g4f_faqa/__init__.py
g4f_faqa/main.py
g4f_faqa-1.0.1.dist-info/WHEEL
g4f_faqa-1.0.1.dist-info/entry_points.txt
g4f_faqa-1.0.1.dist-info/METADATA
g4f_faqa-1.0.1.dist-info/RECORD
