Metadata-Version: 2.3
Name: g4f-faqa
Version: 1.0.1
Summary: A fun project for a friend
Author: M1778
Author-email: M1778 <m1778.pc@gmail.com>
Requires-Dist: pandas>=2.3.3
Requires-Dist: g4f>=0.3.5.0
Requires-Dist: openpyxl>=3.1.5
Requires-Dist: tqdm>=4.67.1
Requires-Dist: python-dotenv>=1.2.1
Requires-Dist: aiohttp>=3.13.2
Requires-Python: >=3.12
